mypy_einsum.py
mypy_einsum-1.0.0.dist-info/LICENSE
mypy_einsum-1.0.0.dist-info/METADATA
mypy_einsum-1.0.0.dist-info/WHEEL
mypy_einsum-1.0.0.dist-info/top_level.txt
mypy_einsum-1.0.0.dist-info/RECORD
