Metadata-Version: 2.1
Name: mypy-einsum
Version: 1.0.0
Summary: Mypy plugin for NumPy/Jax/PyTorch einsum operations
Author-email: Lukas Geiger <lukas.geiger94@gmail.com>
Project-URL: Homepage, https://github.com/lgeiger/mypy-einsum
Project-URL: Issues, https://github.com/lgeiger/mypy-einsum/issues
Classifier: Intended Audience :: Science/Research
Classifier: Intended Audience :: Developers
Classifier: License :: OSI Approved :: MIT License
Classifier: Programming Language :: Python :: 3
Classifier: Operating System :: OS Independent
Requires-Python: >=3.9
License-File: LICENSE
